asgi_logging_middleware/__init__.py
asgi_logging_middleware/middleware.py
asgi_logging_middleware/py.typed
asgi_logging_middleware/utils.py
asgi_logging_middleware-0.2.0.dist-info/METADATA
asgi_logging_middleware-0.2.0.dist-info/WHEEL
asgi_logging_middleware-0.2.0.dist-info/licenses/LICENSE
asgi_logging_middleware-0.2.0.dist-info/RECORD
