Metadata-Version: 2.4
Name: asgi-logging-middleware
Version: 0.2.0
Summary: ASGI middleware for logging HTTP requests and responses. Fork of asgi-logger.
License-Expression: MIT
License-File: LICENSE
Keywords: ASGI,logging,middleware
Author: Marcelo Trylesinski
Author-email: marcelotryle@gmail.com
Maintainer: Vitalija Alisauskaite
Maintainer-email: v.alishauskaite@gmail.com
Requires-Python: >=3.10
Classifier: Topic :: Software Development :: Libraries :: Python Modules
Classifier: Intended Audience :: Developers
Classifier: Operating System :: OS Independent
Classifier: Programming Language :: Python :: 3
Classifier: Programming Language :: Python :: 3.10
Classifier: Programming Language :: Python :: 3.11
Classifier: Programming Language :: Python :: 3.12
Requires-Dist: asgiref (>=3.4.1,<4)
Project-URL: Repository, https://github.com/alv2017/asgi-logging-middleware
